Workbook

Sheet Overview
A1: Guyana Open Orders Tracker
A2: Government, private-sector oil and gas, and multilateral opportunities
A3: Snapshot date | B3: 46278
A5: Total open items | C5: Government | E5: Private sector | G5: Multilateral
A6: =COUNTA('All Open Orders'!A5:A200) -> 47 | C6: =COUNTIF('All Open Orders'!B5:B200,"Government") -> 28 | E6: =COUNTIF('All Open Orders'!B5:B200,"Private") -> 18 | G6: =COUNTIF('All Open Orders'!B5:B200,"Multilateral") -> 1
A8: Known deadlines | C8: Deadline to verify | E8: Due within 7 days | G8: Due within 21 days
A9: =COUNT('All Open Orders'!G5:G200) -> 44 | C9: =COUNTBLANK('All Open Orders'!G5:G51) -> 3 | E9: =COUNTIFS('All Open Orders'!G5:G200,">="&$B$3,'All Open Orders'!G5:G200,"<="&$B$3+7) -> 2 | G9: =COUNTIFS('All Open Orders'!G5:G200,">="&$B$3,'All Open Orders'!G5:G200,"<="&$B$3+21) -> 21
A12: How to use this workbook
A13: • Start with All Open Orders, then filter by buyer type, category, deadline, or buyer.
A14: • Red deadline cells mean the closing date could not be verified. Confirm those notices before spending money or preparing a bid.
A15: • Where exact quantities are not public, the sheet says so. Obtain the full tender document or bill of quantities from the buyer.
A16: • Private oil and gas notices commonly require a Guyana Local Content Certificate or proof of application.
A17: • The Verify First tab contains additional postings that may be open but were not counted because the deadline or details could not be confirmed.
A20: Important limitation
A21: This is a snapshot as of 13 September 2026, not a guarantee that every item remains open after that date. Buyer notices control. Three counted items have deadlines that still need verification. Exact quantities are often withheld from public notices and appear only in paid or collected bid documents.

Sheet All Open Orders
A1: All Open Orders
A2: Open opportunities identified on 13 September 2026. Total: 47
A4: ID | B4: Buyer type | C4: Buyer / procuring entity | D4: Opportunity | E4: Reference | F4: Category | G4: Deadline | H4: Days from snapshot | I4: Deadline detail | J4: Public quantity / scope | K4: Quantity detail status | L4: Official source | M4: Notes
A5: GY-026 | B5: Government | C5: Ministry of Health | D5: Design and Supervision of the National Public Health Reference Laboratory Building (World Bank Guyana One Health Project; consulting firms EOI) | E5: GY-HSDU-MOH-561852-CS-CQS | F5: Consulting | G5: 46280 | H5: =G5-Overview!$B$3 -> 2 | I5: 15 Sep 2026 (extended) | J5: Deliverables in EOI document. | K5: Public scope stated; exact quantity not listed | L5: Official DPI notice | M5: Consulting services only, not goods
A6: GY-046 | B6: Private | C6: Tenaris Guyana | D6: Manpower and Crewing Services (Master Services Agreement) | E6: RFQ | F6: Services | G6: 46283 | H6: =G6-Overview!$B$3 -> 5 | I6: 18 Sep 2026 | J6: Master Services Agreement for on-demand manpower/crewing. | K6: Public scope stated; exact quantity not listed | L6: Local Content Register | M6: Local Content Certificate generally required
A7: GY-025 | B7: Government | C7: Ministry of Housing / CHPA | D7: Invitation for Expressions of Interest: Construction of 400 Square Feet Houses under the Social Housing Programme (low-income flat units: 1 bedroom, toilet & bath, ceiling, tiles, basic kitchen cupboard; all regions) | E7: (EOI) | F7: Works | G7: 46286 | H7: =G7-Overview!$B$3 -> 8 | I7: 21 Sep 2026, 15:00 | J7: EOI to Chairman, CHPA Board, Plantation Houston, Mandela to Eccles Highway, EBD. | K7: Public scope stated; exact quantity not listed | L7: Official CHPA notice
A8: GY-045 | B8: Private | C8: G-Boats Inc. | D8: Week 33 Tender - operating supplies incl. PPE | E8: RFQ | F8: Goods | G8: 46286 | H8: =G8-Overview!$B$3 -> 8 | I8: 21 Sep 2026 | J8: Operating supplies: general supplies, PPE & safety (item list by request: eco.g-boats.bids@chouest.com). | K8: Public scope stated; exact quantity not listed | L8: Local Content Register | M8: Local Content Certificate generally required
A9: GY-007 | B9: Government | C9: Guyana Water Inc. (Ministry of Public Utilities and Aviation) | D9: Rehabilitation works for the Bartica 5 Miles Raw Water Intake Structure, Bartica, Region 7 | E9: GWI-W209-2026 | F9: Works | G9: 46287 | H9: =G9-Overview!$B$3 -> 9 | I9: 22 Sep 2026, 09:00 | J9: Scope not stated publicly; GoG budget G$38M. Work items in paid bid documents (G$5,000, GWI Cashier, Shelter Belt). | K9: Full detail in tender documents | L9: Official eProcure notice
A10: GY-044 | B10: Private | C10: Guyana Deepwater Operations (SBM Offshore) | D10: RFI: IT Hardware Equipment Disposal | E10: GDO-SCM-119 | F10: Services | G10: 46288 | H10: =G10-Overview!$B$3 -> 10 | I10: 23 Sep 2026 | J10: IT hardware equipment disposal. | K10: Public scope stated; exact quantity not listed | L10: Local Content Register | M10: Local Content Certificate generally required
A11: GY-042 | B11: Private | C11: Halliburton Guyana | D11: Compressor Maintenance Services (parts + onsite/offsite maintenance, repairs, overhaul) | E11: EOI | F11: Services | G11: 46290 | H11: =G11-Overview!$B$3 -> 12 | I11: 25 Sep 2026 | J11: Compressor parts + onsite/offsite maintenance, repairs, overhaul. | K11: Public scope stated; exact quantity not listed | L11: Local Content Register | M11: Local Content Certificate generally required
A12: GY-043 | B12: Private | C12: Halliburton Guyana | D12: Crane Maintenance Services | E12: EOI | F12: Services | G12: 46290 | H12: =G12-Overview!$B$3 -> 12 | I12: 25 Sep 2026 | J12: Crane maintenance (details in notice documents). | K12: Public scope stated; exact quantity not listed | L12: Local Content Register | M12: Local Content Certificate generally required
A13: GY-041 | B13: Private | C13: Oceaneering Guyana | D13: Inland Transportation & Logistics Services - pre-qualify local suppliers | E13: RFI | F13: Services | G13: 46291 | H13: =G13-Overview!$B$3 -> 13 | I13: 26 Sep 2026 | J13: Inland transport and logistics; pre-qualify local suppliers. | K13: Public scope stated; exact quantity not listed | L13: Local Content Register | M13: Local Content Certificate generally required
A14: GY-019 | B14: Government | C14: Guyana Power & Light Inc. | D14: Engineering, Procurement and Construction of L5 69kV Double Circuit Transmission Line on Steel Monopoles (Kingston & Sophia substations interconnection) | E14: SEMD-002-2026 | F14: Works | G14: 46294 | H14: =G14-Overview!$B$3 -> 16 | I14: 29 Sep 2026 | J14: Line length, monopole counts and duration in purchased bid documents (GPL Program Execution Unit, 103 Carmichael Street, Georgetown). | K14: Full detail in tender documents | L14: Official GPL notice | M14: Listed on gplinc.com only (not on eprocure portal)
A15: GY-009 | B15: Government | C15: Guyana Water Inc. (Ministry of Public Utilities and Aviation) | D15: Design, Supply, Installation and Testing of Air Conditioning Units + electrical works + networking cables for GWI Corporate Complex | E15: GWI-GOG-W214-2026 | F15: Goods/Works | G15: 46294 | H15: =G15-Overview!$B$3 -> 16 | I15: 29 Sep 2026, 09:00 | J15: Unit counts and tonnage in paid bid documents only. | K15: Full detail in tender documents | L15: Official eProcure notice
A16: GY-010 | B16: Government | C16: Guyana Water Inc. (Ministry of Public Utilities and Aviation) | D16: Drilling of Potable Water Well at Long Creek, Linden Soesdyke Highway, Region 4 | E16: GWI-GOG-W215-2026 | F16: Works | G16: 46294 | H16: =G16-Overview!$B$3 -> 16 | I16: 29 Sep 2026, 09:00 | J16: 1 well; depth/diameter specs in paid bid documents. | K16: Full detail in tender documents | L16: Official eProcure notice
A17: GY-011 | B17: Government | C17: Guyana Water Inc. (Ministry of Public Utilities and Aviation) | D17: Drilling of Potable Water Well at Lusignan, ECD, Region 4 | E17: GWI-GOG-W216-2026 | F17: Works | G17: 46294 | H17: =G17-Overview!$B$3 -> 16 | I17: 29 Sep 2026, 09:00 | J17: 1 well; specs in paid bid documents. | K17: Full detail in tender documents | L17: Official eProcure notice
A18: GY-012 | B18: Government | C18: Guyana Water Inc. (Ministry of Public Utilities and Aviation) | D18: Drilling of Potable Water Well at Shirley Field Ridley Square, Georgetown, Region 4 | E18: GWI-GOG-W217-2026 | F18: Works | G18: 46294 | H18: =G18-Overview!$B$3 -> 16 | I18: 29 Sep 2026, 09:00 | J18: 1 well; specs in paid bid documents. | K18: Full detail in tender documents | L18: Official eProcure notice
A19: GY-008 | B19: Government | C19: Guyana Water Inc. (Ministry of Public Utilities and Aviation) | D19: Installation of Kettle Filters at Better Hope Water Treatment Plant, ECD, Region 4 | E19: GWI-W213-2026 | F19: Goods/Works | G19: 46294 | H19: =G19-Overview!$B$3 -> 16 | I19: 29 Sep 2026, 09:00 | J19: Filter count, sizes, capacities in paid bid documents only (G$5,000). | K19: Full detail in tender documents | L19: Official eProcure notice
A20: GY-023 | B20: Government | C20: Ministry of Agriculture | D20: Development and Finalisation of the National Water Policy and Action Plan (consulting EOI) | E20: (EOI, ref unknown) | F20: Consulting | G20: 46294 | H20: =G20-Overview!$B$3 -> 16 | I20: 29 Sep 2026, 09:00 (portal-listed; independently unverified) | J20: Deliverables/duration in EOI document (Procurement Dept, Regent & Shiv Chanderpaul Drive, Georgetown). | K20: Public scope stated; exact quantity not listed | L20: Official eProcure notice
A21: GY-024 | B21: Government | C21: The Guyana Oil Company Limited (GUYOIL) | D21: Supply of Petroleum Products (Gasoline, Gasoil, Ultra Low Sulphur Diesel, Jet A-1; FOB and CIF; CIF delivered to one independent port in Georgetown; FOB uplifted from supplier's identified storage) | E21: GUYOIL RFP No. 01/26 | F21: Goods | G21: 46294 | H21: =G21-Overview!$B$3 -> 16 | I21: 29 Sep 2026 | J21: Volumes/specs in RFP documents (GUYOIL Inventory & Procurement Dept). Submissions: tenderbox@guyoil.gy or Tender Box No. 15. Proposals opened 14:00 hrs 29 Sep 2026 at Guyoil Office Complex, Providence, EBD. | K21: Full detail in tender documents | L21: Official DPI notice | M21: State oil company annual fuel supply RFP
A22: GY-021 | B22: Government | C22: Guyana Power & Light Inc. | D22: Supply and Delivery of Transmission & Distribution Materials - Good Hope | E22: GPL-PD-028-2026 | F22: Goods | G22: 46296 | H22: =G22-Overview!$B$3 -> 18 | I22: 1 Oct 2026, 09:00 (authoritative per GPL; eprocure row shows 6 Oct) | J22: Bill of quantities (conductors, poles, hardware, meters) in paid bid documents only. | K22: Full detail in tender documents | L22: Official eProcure notice | M22: NIS/GRA compliance applies to local companies only
A23: GY-013 | B23: Government | C23: Hinterland Electrification Company Inc. (Ministry of Public Utilities and Aviation) | D23: Supply and Delivery of Pole Mounted Transformers for Lethem Power Co. Inc. | E23: LMPC/G/11/2026 (Invitation No. 11) | F23: Goods | G23: 46296 | H23: =G23-Overview!$B$3 -> 18 | I23: 1 Oct 2026, 09:00 | J23: Transformer count, kVA ratings, voltage specs in bid document (downloadable at electricity.gov.gy). 8-week supply period; 2% bid security; bids valid 120 days. | K23: Full detail in tender documents | L23: Official eProcure notice
A24: GY-001 | B24: Government | C24: Ministry of Public Works | D24: Rehabilitation and Upgrade of Mahaica Bridge to Abary Bridge Road Corridor (World Bank IDA financed) | E24: RFB P501759-CW-1 | F24: Works | G24: 46297 | H24: =G24-Overview!$B$3 -> 19 | I24: 2 Oct 2026, 09:00 | J24: 27.1 km dual-carriageway asphalt road (Km 0+00 to 27+10); 10 prestressed precast concrete bridges (10-15 m spans); 750 m precast box culverts; 20,120 m in-situ concrete drains; 17,040 m earthen drains; utility relocation; road furniture. 36-month contract. Bid security US$2,000,000. | K24: Public scope or partial quantity stated | L24: Official eProcure notice | M24: International competitive procurement; open to foreign bidders
A25: GY-040 | B25: Private | C25: Tenaris Guyana | D25: RFID Tags Supplier (printer supplier for RFID tags, material traceability project) | E25: RFI | F25: Goods | G25: 46298 | H25: =G25-Overview!$B$3 -> 20 | I25: 3 Oct 2026 | J25: Printer supplier for RFID tags, material traceability project. | K25: Public scope stated; exact quantity not listed | L25: Local Content Register | M25: Local Content Certificate generally required
A26: GY-038 | B26: Private | C26: CNOOC Petroleum Guyana | D26: Janitorial Services - information gathering | E26: RFI | F26: Services | G26: 46300 | H26: =G26-Overview!$B$3 -> 22 | I26: 5 Oct 2026 | J26: Janitorial services; info gathering from qualified providers. | K26: Public scope stated; exact quantity not listed | L26: Local Content Register | M26: Local Content Certificate generally required
A27: GY-039 | B27: Private | C27: Champion X | D27: ISO Tank Inspections (periodic inspections/testing of ISO tanks in chemical logistics) | E27: RFQ | F27: Services | G27: 46300 | H27: =G27-Overview!$B$3 -> 22 | I27: 5 Oct 2026 | J27: Periodic inspections/testing of ISO tanks in chemical logistics. | K27: Public scope stated; exact quantity not listed | L27: Local Content Register | M27: Local Content Certificate generally required
A28: GY-020 | B28: Government | C28: Guyana Power & Light Inc. | D28: Supply and Delivery of Insulators | E28: GPL-PD-026-2026 | F28: Goods | G28: 46301 | H28: =G28-Overview!$B$3 -> 23 | I28: 6 Oct 2026, 09:00 | J28: Quantities by insulator type and voltage rating in paid bid documents (G$5,000; from 27 Aug 2026). | K28: Full detail in tender documents | L28: Official eProcure notice | M28: NIS/GRA compliance applies to local companies only - foreign firms exempt
A29: GY-016 | B29: Government | C29: Guyana Water Inc. (Ministry of Public Utilities and Aviation) | D29: Supply and Installation of Transmission Mains at Adventure, Region 6 (Lots 1-4) - CDB WSIP | E29: GWI-CDB-W104-2026 | F29: Works/Goods | G29: 46301 | H29: =G29-Overview!$B$3 -> 23 | I29: 6 Oct 2026, 09:00 | J29: Approx 20 km of 400 mm PVC pipes, Tain to Village 47, Corentyne. Lots: 1 Tain-Alness; 2 Alness-Kilmarnock; 3 Kilmarnock-Kiltarin; 4 Kiltarin-Village 47. | K29: Public scope or partial quantity stated | L29: Official eProcure notice | M29: ICB; CDB member-country firms
A30: GY-015 | B30: Government | C30: Guyana Water Inc. (Ministry of Public Utilities and Aviation) | D30: Supply and Installation of Transmission Mains at Bath, West Coast Berbice, Region 5 (Lots 1-4) - CDB WSIP | E30: GWI-CDB-W100-2026 | F30: Works/Goods | G30: 46301 | H30: =G30-Overview!$B$3 -> 23 | I30: 6 Oct 2026, 09:00 | J30: Approx 20.1 km of 300 mm PVC pipes, Jacoba to Experiment Housing Scheme. Lots: 1 Jacoba-Union; 2 Union-St. John; 3 St. John-Bath; 4 Bath-No. 7 Village & Experiment HS. | K30: Public scope or partial quantity stated | L30: Official GWI notice | M30: ICB; CDB member-country firms
A31: GY-014 | B31: Government | C31: Guyana Water Inc. (Ministry of Public Utilities and Aviation) | D31: Supply and Installation of Transmission Mains at Leguan, Region 3 (single lot) - CDB Water Supply Improvement Project | E31: GWI-CDB-W101-2026 | F31: Works/Goods | G31: 46301 | H31: =G31-Overview!$B$3 -> 23 | I31: 6 Oct 2026, 09:00 | J31: Approx 4.4 km of 150 mm PVC pipes on Leguan Island. | K31: Public scope or partial quantity stated | L31: Official eProcure notice | M31: ICB; CDB member-country firms/JVs; turnover, cash-flow and experience thresholds
A32: GY-017 | B32: Government | C32: Guyana Water Inc. (Ministry of Public Utilities and Aviation) | D32: Supply and Installation of Transmission Mains at Wakenaam, Region 3 (single lot) - CDB WSIP | E32: GWI-CDB-W102-2026 | F32: Works/Goods | G32: 46301 | H32: =G32-Overview!$B$3 -> 23 | I32: 6 Oct 2026, 09:00 | J32: Approx 6.5 km of 200 mm PVC pipes on Wakenaam Island. | K32: Public scope or partial quantity stated | L32: Official eProcure notice | M32: ICB; CDB member-country firms
A33: GY-018 | B33: Government | C33: Guyana Water Inc. (Ministry of Public Utilities and Aviation) | D33: Supply and Installation of Transmission Mains at Walton Hall to Charity, Region 2 (Lots 1-4) - CDB WSIP | E33: GWI-CDB-W103-2026 | F33: Works/Goods | G33: 46301 | H33: =G33-Overview!$B$3 -> 23 | I33: 6 Oct 2026, 09:00 | J33: Approx 17.1 km of 300 mm PVC pipes, Walton Hall to Charity, Essequibo. Lots: 1 Walton Hall-Bounty Hall; 2 Bounty Hall-Maria's Delight; 3 Maria's Delight-Berks; 4 Berks-Charity. | K33: Public scope or partial quantity stated | L33: Official eProcure notice | M33: ICB; CDB member-country firms
A34: GY-006 | B34: Government | C34: Ministry of Housing / Central Housing & Planning Authority (CHPA) | D34: Drilling of Potable Water Well - Region 10 | E34: Region 10 - 1 lot | F34: Works | G34: 46301 | H34: =G34-Overview!$B$3 -> 23 | I34: 6 Oct 2026, 09:00 | J34: Amelia's Ward Phase 4. Well counts and depths are in the paid bid documents (G$10,000, CHPA Cashier, Plantation Houston). 10-month construction period. One lot per bidder per project area. | K34: Full detail in tender documents | L34: Official CHPA notice | M34: Open to all eligible bidders
A35: GY-003 | B35: Government | C35: Ministry of Housing / Central Housing & Planning Authority (CHPA) | D35: Drilling of Potable Water Wells - Region 3, Lots 1-3 | E35: Regions 3 - Lots 1-3 | F35: Works | G35: 46301 | H35: =G35-Overview!$B$3 -> 23 | I35: 6 Oct 2026, 09:00 | J35: Meten-Meer-Zorg Phase 2, Wales Phases 1 and 2, and Stewartville. Well counts and depths are in the paid bid documents (G$10,000, CHPA Cashier, Plantation Houston). 10-month construction period. One lot per bidder per project area. | K35: Full detail in tender documents | L35: Official CHPA notice | M35: Open to all eligible bidders
... A48: GY-002 | B48: Government | C48: Ministry of Public Service, Government Efficiency and Implementation | D48: Provision of Security Services at six (6) locations | E48: (not stated) | F48: Services | G48: 46308 | H48: =G48-Overview!$B$3 -> 30 | I48: 13 Oct 2026, 09:00 | J48: Six locations (not named); guard counts/posts/shifts and contract duration not stated publicly - in paid bid documents (G$3,000, 164 Waterloo Street, Georgetown). Bid security 1% of contract sum; bids valid 120 days. | K48: Full detail in tender documents | L48: Official eProcure notice | M48: NIS and GRA compliance certificates required
A49: GY-027 | B49: Government | C49: Ministry of Home Affairs | D49: Infrastructural Works to Suddie Police Station - Guyana Police Force, Region No. 2 | E49: (not published) | F49: Works | I49: Deadline not verified (DPI post 9 Sep 2026) | J49: Scope not publicly stated; full scope in bid document. Advert is a scanned image; deadline could not be verified. | K49: Full detail in tender documents | L49: Official DPI notice | M49: NEW - verify deadline on advert image before acting
A50: GY-028 | B50: Government | C50: Ministry of Home Affairs | D50: Procurement of Office Equipment & Furniture, Lots 1-2 - Guyana Police Force | E50: (not published) | F50: Goods | I50: Deadline not verified (DPI post 9 Sep 2026) | J50: Items per lot not publicly stated. Bid documents from Finance Dept, Ministry of Home Affairs, Lot 6 Brickdam, Georgetown (G$3,000 fee). | K50: Full detail in tender documents | L50: Official DPI notice | M50: NEW - verify deadline on advert image before acting
A51: GY-047 | B51: Multilateral | C51: UNDP Guyana (multilateral) | D51: Provision of Unarmed Security Services for the United Nations Offices (Long-Term Agreement) | E51: UNDP-GUY-00034 | F51: Services | I51: Deadline not verified (bids via UNDP Quantum portal) | J51: Unarmed private security guard services: access control, CCTV/alarm monitoring, perimeter security, patrolling, fire-drill assistance. Full TOR on notice page. | K51: Public scope stated; exact quantity not listed | L51: UNDP procurement notice | M51: Verify deadline on notice page before acting

Sheet Government
A1: Government
A2: Open opportunities identified on 13 September 2026. Total: 28
A4: ID | B4: Buyer type | C4: Buyer / procuring entity | D4: Opportunity | E4: Reference | F4: Category | G4: Deadline | H4: Days from snapshot | I4: Deadline detail | J4: Public quantity / scope | K4: Quantity detail status | L4: Official source | M4: Notes
A5: GY-026 | B5: Government | C5: Ministry of Health | D5: Design and Supervision of the National Public Health Reference Laboratory Building (World Bank Guyana One Health Project; consulting firms EOI) | E5: GY-HSDU-MOH-561852-CS-CQS | F5: Consulting | G5: 46280 | H5: =G5-Overview!$B$3 -> 2 | I5: 15 Sep 2026 (extended) | J5: Deliverables in EOI document. | K5: Public scope stated; exact quantity not listed | L5: Official DPI notice | M5: Consulting services only, not goods
A6: GY-025 | B6: Government | C6: Ministry of Housing / CHPA | D6: Invitation for Expressions of Interest: Construction of 400 Square Feet Houses under the Social Housing Programme (low-income flat units: 1 bedroom, toilet & bath, ceiling, tiles, basic kitchen cupboard; all regions) | E6: (EOI) | F6: Works | G6: 46286 | H6: =G6-Overview!$B$3 -> 8 | I6: 21 Sep 2026, 15:00 | J6: EOI to Chairman, CHPA Board, Plantation Houston, Mandela to Eccles Highway, EBD. | K6: Public scope stated; exact quantity not listed | L6: Official CHPA notice
A7: GY-007 | B7: Government | C7: Guyana Water Inc. (Ministry of Public Utilities and Aviation) | D7: Rehabilitation works for the Bartica 5 Miles Raw Water Intake Structure, Bartica, Region 7 | E7: GWI-W209-2026 | F7: Works | G7: 46287 | H7: =G7-Overview!$B$3 -> 9 | I7: 22 Sep 2026, 09:00 | J7: Scope not stated publicly; GoG budget G$38M. Work items in paid bid documents (G$5,000, GWI Cashier, Shelter Belt). | K7: Full detail in tender documents | L7: Official eProcure notice
A8: GY-019 | B8: Government | C8: Guyana Power & Light Inc. | D8: Engineering, Procurement and Construction of L5 69kV Double Circuit Transmission Line on Steel Monopoles (Kingston & Sophia substations interconnection) | E8: SEMD-002-2026 | F8: Works | G8: 46294 | H8: =G8-Overview!$B$3 -> 16 | I8: 29 Sep 2026 | J8: Line length, monopole counts and duration in purchased bid documents (GPL Program Execution Unit, 103 Carmichael Street, Georgetown). | K8: Full detail in tender documents | L8: Official GPL notice | M8: Listed on gplinc.com only (not on eprocure portal)
A9: GY-009 | B9: Government | C9: Guyana Water Inc. (Ministry of Public Utilities and Aviation) | D9: Design, Supply, Installation and Testing of Air Conditioning Units + electrical works + networking cables for GWI Corporate Complex | E9: GWI-GOG-W214-2026 | F9: Goods/Works | G9: 46294 | H9: =G9-Overview!$B$3 -> 16 | I9: 29 Sep 2026, 09:00 | J9: Unit counts and tonnage in paid bid documents only. | K9: Full detail in tender documents | L9: Official eProcure notice
A10: GY-010 | B10: Government | C10: Guyana Water Inc. (Ministry of Public Utilities and Aviation) | D10: Drilling of Potable Water Well at Long Creek, Linden Soesdyke Highway, Region 4 | E10: GWI-GOG-W215-2026 | F10: Works | G10: 46294 | H10: =G10-Overview!$B$3 -> 16 | I10: 29 Sep 2026, 09:00 | J10: 1 well; depth/diameter specs in paid bid documents. | K10: Full detail in tender documents | L10: Official eProcure notice
A11: GY-011 | B11: Government | C11: Guyana Water Inc. (Ministry of Public Utilities and Aviation) | D11: Drilling of Potable Water Well at Lusignan, ECD, Region 4 | E11: GWI-GOG-W216-2026 | F11: Works | G11: 46294 | H11: =G11-Overview!$B$3 -> 16 | I11: 29 Sep 2026, 09:00 | J11: 1 well; specs in paid bid documents. | K11: Full detail in tender documents | L11: Official eProcure notice
A12: GY-012 | B12: Government | C12: Guyana Water Inc. (Ministry of Public Utilities and Aviation) | D12: Drilling of Potable Water Well at Shirley Field Ridley Square, Georgetown, Region 4 | E12: GWI-GOG-W217-2026 | F12: Works | G12: 46294 | H12: =G12-Overview!$B$3 -> 16 | I12: 29 Sep 2026, 09:00 | J12: 1 well; specs in paid bid documents. | K12: Full detail in tender documents | L12: Official eProcure notice
A13: GY-008 | B13: Government | C13: Guyana Water Inc. (Ministry of Public Utilities and Aviation) | D13: Installation of Kettle Filters at Better Hope Water Treatment Plant, ECD, Region 4 | E13: GWI-W213-2026 | F13: Goods/Works | G13: 46294 | H13: =G13-Overview!$B$3 -> 16 | I13: 29 Sep 2026, 09:00 | J13: Filter count, sizes, capacities in paid bid documents only (G$5,000). | K13: Full detail in tender documents | L13: Official eProcure notice
A14: GY-023 | B14: Government | C14: Ministry of Agriculture | D14: Development and Finalisation of the National Water Policy and Action Plan (consulting EOI) | E14: (EOI, ref unknown) | F14: Consulting | G14: 46294 | H14: =G14-Overview!$B$3 -> 16 | I14: 29 Sep 2026, 09:00 (portal-listed; independently unverified) | J14: Deliverables/duration in EOI document (Procurement Dept, Regent & Shiv Chanderpaul Drive, Georgetown). | K14: Public scope stated; exact quantity not listed | L14: Official eProcure notice
A15: GY-024 | B15: Government | C15: The Guyana Oil Company Limited (GUYOIL) | D15: Supply of Petroleum Products (Gasoline, Gasoil, Ultra Low Sulphur Diesel, Jet A-1; FOB and CIF; CIF delivered to one independent port in Georgetown; FOB uplifted from supplier's identified storage) | E15: GUYOIL RFP No. 01/26 | F15: Goods | G15: 46294 | H15: =G15-Overview!$B$3 -> 16 | I15: 29 Sep 2026 | J15: Volumes/specs in RFP documents (GUYOIL Inventory & Procurement Dept). Submissions: tenderbox@guyoil.gy or Tender Box No. 15. Proposals opened 14:00 hrs 29 Sep 2026 at Guyoil Office Complex, Providence, EBD. | K15: Full detail in tender documents | L15: Official DPI notice | M15: State oil company annual fuel supply RFP
A16: GY-021 | B16: Government | C16: Guyana Power & Light Inc. | D16: Supply and Delivery of Transmission & Distribution Materials - Good Hope | E16: GPL-PD-028-2026 | F16: Goods | G16: 46296 | H16: =G16-Overview!$B$3 -> 18 | I16: 1 Oct 2026, 09:00 (authoritative per GPL; eprocure row shows 6 Oct) | J16: Bill of quantities (conductors, poles, hardware, meters) in paid bid documents only. | K16: Full detail in tender documents | L16: Official eProcure notice | M16: NIS/GRA compliance applies to local companies only
A17: GY-013 | B17: Government | C17: Hinterland Electrification Company Inc. (Ministry of Public Utilities and Aviation) | D17: Supply and Delivery of Pole Mounted Transformers for Lethem Power Co. Inc. | E17: LMPC/G/11/2026 (Invitation No. 11) | F17: Goods | G17: 46296 | H17: =G17-Overview!$B$3 -> 18 | I17: 1 Oct 2026, 09:00 | J17: Transformer count, kVA ratings, voltage specs in bid document (downloadable at electricity.gov.gy). 8-week supply period; 2% bid security; bids valid 120 days. | K17: Full detail in tender documents | L17: Official eProcure notice
A18: GY-001 | B18: Government | C18: Ministry of Public Works | D18: Rehabilitation and Upgrade of Mahaica Bridge to Abary Bridge Road Corridor (World Bank IDA financed) | E18: RFB P501759-CW-1 | F18: Works | G18: 46297 | H18: =G18-Overview!$B$3 -> 19 | I18: 2 Oct 2026, 09:00 | J18: 27.1 km dual-carriageway asphalt road (Km 0+00 to 27+10); 10 prestressed precast concrete bridges (10-15 m spans); 750 m precast box culverts; 20,120 m in-situ concrete drains; 17,040 m earthen drains; utility relocation; road furniture. 36-month contract. Bid security US$2,000,000. | K18: Public scope or partial quantity stated | L18: Official eProcure notice | M18: International competitive procurement; open to foreign bidders
A19: GY-020 | B19: Government | C19: Guyana Power & Light Inc. | D19: Supply and Delivery of Insulators | E19: GPL-PD-026-2026 | F19: Goods | G19: 46301 | H19: =G19-Overview!$B$3 -> 23 | I19: 6 Oct 2026, 09:00 | J19: Quantities by insulator type and voltage rating in paid bid documents (G$5,000; from 27 Aug 2026). | K19: Full detail in tender documents | L19: Official eProcure notice | M19: NIS/GRA compliance applies to local companies only - foreign firms exempt
A20: GY-016 | B20: Government | C20: Guyana Water Inc. (Ministry of Public Utilities and Aviation) | D20: Supply and Installation of Transmission Mains at Adventure, Region 6 (Lots 1-4) - CDB WSIP | E20: GWI-CDB-W104-2026 | F20: Works/Goods | G20: 46301 | H20: =G20-Overview!$B$3 -> 23 | I20: 6 Oct 2026, 09:00 | J20: Approx 20 km of 400 mm PVC pipes, Tain to Village 47, Corentyne. Lots: 1 Tain-Alness; 2 Alness-Kilmarnock; 3 Kilmarnock-Kiltarin; 4 Kiltarin-Village 47. | K20: Public scope or partial quantity stated | L20: Official eProcure notice | M20: ICB; CDB member-country firms
A21: GY-015 | B21: Government | C21: Guyana Water Inc. (Ministry of Public Utilities and Aviation) | D21: Supply and Installation of Transmission Mains at Bath, West Coast Berbice, Region 5 (Lots 1-4) - CDB WSIP | E21: GWI-CDB-W100-2026 | F21: Works/Goods | G21: 46301 | H21: =G21-Overview!$B$3 -> 23 | I21: 6 Oct 2026, 09:00 | J21: Approx 20.1 km of 300 mm PVC pipes, Jacoba to Experiment Housing Scheme. Lots: 1 Jacoba-Union; 2 Union-St. John; 3 St. John-Bath; 4 Bath-No. 7 Village & Experiment HS. | K21: Public scope or partial quantity stated | L21: Official GWI notice | M21: ICB; CDB member-country firms
A22: GY-014 | B22: Government | C22: Guyana Water Inc. (Ministry of Public Utilities and Aviation) | D22: Supply and Installation of Transmission Mains at Leguan, Region 3 (single lot) - CDB Water Supply Improvement Project | E22: GWI-CDB-W101-2026 | F22: Works/Goods | G22: 46301 | H22: =G22-Overview!$B$3 -> 23 | I22: 6 Oct 2026, 09:00 | J22: Approx 4.4 km of 150 mm PVC pipes on Leguan Island. | K22: Public scope or partial quantity stated | L22: Official eProcure notice | M22: ICB; CDB member-country firms/JVs; turnover, cash-flow and experience thresholds
A23: GY-017 | B23: Government | C23: Guyana Water Inc. (Ministry of Public Utilities and Aviation) | D23: Supply and Installation of Transmission Mains at Wakenaam, Region 3 (single lot) - CDB WSIP | E23: GWI-CDB-W102-2026 | F23: Works/Goods | G23: 46301 | H23: =G23-Overview!$B$3 -> 23 | I23: 6 Oct 2026, 09:00 | J23: Approx 6.5 km of 200 mm PVC pipes on Wakenaam Island. | K23: Public scope or partial quantity stated | L23: Official eProcure notice | M23: ICB; CDB member-country firms
A24: GY-018 | B24: Government | C24: Guyana Water Inc. (Ministry of Public Utilities and Aviation) | D24: Supply and Installation of Transmission Mains at Walton Hall to Charity, Region 2 (Lots 1-4) - CDB WSIP | E24: GWI-CDB-W103-2026 | F24: Works/Goods | G24: 46301 | H24: =G24-Overview!$B$3 -> 23 | I24: 6 Oct 2026, 09:00 | J24: Approx 17.1 km of 300 mm PVC pipes, Walton Hall to Charity, Essequibo. Lots: 1 Walton Hall-Bounty Hall; 2 Bounty Hall-Maria's Delight; 3 Maria's Delight-Berks; 4 Berks-Charity. | K24: Public scope or partial quantity stated | L24: Official eProcure notice | M24: ICB; CDB member-country firms
A25: GY-006 | B25: Government | C25: Ministry of Housing / Central Housing & Planning Authority (CHPA) | D25: Drilling of Potable Water Well - Region 10 | E25: Region 10 - 1 lot | F25: Works | G25: 46301 | H25: =G25-Overview!$B$3 -> 23 | I25: 6 Oct 2026, 09:00 | J25: Amelia's Ward Phase 4. Well counts and depths are in the paid bid documents (G$10,000, CHPA Cashier, Plantation Houston). 10-month construction period. One lot per bidder per project area. | K25: Full detail in tender documents | L25: Official CHPA notice | M25: Open to all eligible bidders
A26: GY-003 | B26: Government | C26: Ministry of Housing / Central Housing & Planning Authority (CHPA) | D26: Drilling of Potable Water Wells - Region 3, Lots 1-3 | E26: Regions 3 - Lots 1-3 | F26: Works | G26: 46301 | H26: =G26-Overview!$B$3 -> 23 | I26: 6 Oct 2026, 09:00 | J26: Meten-Meer-Zorg Phase 2, Wales Phases 1 and 2, and Stewartville. Well counts and depths are in the paid bid documents (G$10,000, CHPA Cashier, Plantation Houston). 10-month construction period. One lot per bidder per project area. | K26: Full detail in tender documents | L26: Official CHPA notice | M26: Open to all eligible bidders
A27: GY-004 | B27: Government | C27: Ministry of Housing / Central Housing & Planning Authority (CHPA) | D27: Drilling of Potable Water Wells - Region 4, Lots 1-6 | E27: Region 4 - Lots 1-6 | F27: Works | G27: 46301 | H27: =G27-Overview!$B$3 -> 23 | I27: 6 Oct 2026, 09:00 | J27: Cummings Lodge Industrial Zone, Lusignan, Non Pareil Phase 1, Success Phase 2, Diamond, and Ogle Highway. Well counts and depths are in the paid bid documents (G$10,000, CHPA Cashier, Plantation Houston). 10-month construction period. One lot per bidder per project area. | K27: Full detail in tender documents | L27: Official CHPA notice | M27: Open to all eligible bidders
A28: GY-005 | B28: Government | C28: Ministry of Housing / Central Housing & Planning Authority (CHPA) | D28: Drilling of Potable Water Wells - Region 6, Lots 1-4 | E28: Region 6 - Lots 1-4 | F28: Works | G28: 46301 | H28: =G28-Overview!$B$3 -> 23 | I28: 6 Oct 2026, 09:00 | J28: Palmyra, No. 75 Village, Moleson Creek Phase, and Providence. Well counts and depths are in the paid bid documents (G$10,000, CHPA Cashier, Plantation Houston). 10-month construction period. One lot per bidder per project area. | K28: Full detail in tender documents | L28: Official CHPA notice | M28: Open to all eligible bidders
A29: GY-022 | B29: Government | C29: Guyana Power & Light Inc. | D29: Electrification Project - Linden Soesdyke Highway R2, Lots 1-2 | E29: GPL-PD-030-2026 | F29: Works | G29: 46303 | H29: =G29-Overview!$B$3 -> 25 | I29: 8 Oct 2026, 09:00 | J29: Per-lot scope (line lengths, pole counts, transformers, service connections) in paid bid documents only (from 14 Sep 2026). | K29: Full detail in tender documents | L29: Official eProcure notice | M29: NIS/GRA compliance applies to local companies only
A30: GY-002 | B30: Government | C30: Ministry of Public Service, Government Efficiency and Implementation | D30: Provision of Security Services at six (6) locations | E30: (not stated) | F30: Services | G30: 46308 | H30: =G30-Overview!$B$3 -> 30 | I30: 13 Oct 2026, 09:00 | J30: Six locations (not named); guard counts/posts/shifts and contract duration not stated publicly - in paid bid documents (G$3,000, 164 Waterloo Street, Georgetown). Bid security 1% of contract sum; bids valid 120 days. | K30: Full detail in tender documents | L30: Official eProcure notice | M30: NIS and GRA compliance certificates required
A31: GY-027 | B31: Government | C31: Ministry of Home Affairs | D31: Infrastructural Works to Suddie Police Station - Guyana Police Force, Region No. 2 | E31: (not published) | F31: Works | I31: Deadline not verified (DPI post 9 Sep 2026) | J31: Scope not publicly stated; full scope in bid document. Advert is a scanned image; deadline could not be verified. | K31: Full detail in tender documents | L31: Official DPI notice | M31: NEW - verify deadline on advert image before acting
A32: GY-028 | B32: Government | C32: Ministry of Home Affairs | D32: Procurement of Office Equipment & Furniture, Lots 1-2 - Guyana Police Force | E32: (not published) | F32: Goods | I32: Deadline not verified (DPI post 9 Sep 2026) | J32: Items per lot not publicly stated. Bid documents from Finance Dept, Ministry of Home Affairs, Lot 6 Brickdam, Georgetown (G$3,000 fee). | K32: Full detail in tender documents | L32: Official DPI notice | M32: NEW - verify deadline on advert image before acting

Sheet Private & Multilateral
A1: Private & Multilateral
A2: Open opportunities identified on 13 September 2026. Total: 19
A4: ID | B4: Buyer type | C4: Buyer / procuring entity | D4: Opportunity | E4: Reference | F4: Category | G4: Deadline | H4: Days from snapshot | I4: Deadline detail | J4: Public quantity / scope | K4: Quantity detail status | L4: Official source | M4: Notes
A5: GY-046 | B5: Private | C5: Tenaris Guyana | D5: Manpower and Crewing Services (Master Services Agreement) | E5: RFQ | F5: Services | G5: 46283 | H5: =G5-Overview!$B$3 -> 5 | I5: 18 Sep 2026 | J5: Master Services Agreement for on-demand manpower/crewing. | K5: Public scope stated; exact quantity not listed | L5: Local Content Register | M5: Local Content Certificate generally required
A6: GY-045 | B6: Private | C6: G-Boats Inc. | D6: Week 33 Tender - operating supplies incl. PPE | E6: RFQ | F6: Goods | G6: 46286 | H6: =G6-Overview!$B$3 -> 8 | I6: 21 Sep 2026 | J6: Operating supplies: general supplies, PPE & safety (item list by request: eco.g-boats.bids@chouest.com). | K6: Public scope stated; exact quantity not listed | L6: Local Content Register | M6: Local Content Certificate generally required
A7: GY-044 | B7: Private | C7: Guyana Deepwater Operations (SBM Offshore) | D7: RFI: IT Hardware Equipment Disposal | E7: GDO-SCM-119 | F7: Services | G7: 46288 | H7: =G7-Overview!$B$3 -> 10 | I7: 23 Sep 2026 | J7: IT hardware equipment disposal. | K7: Public scope stated; exact quantity not listed | L7: Local Content Register | M7: Local Content Certificate generally required
A8: GY-042 | B8: Private | C8: Halliburton Guyana | D8: Compressor Maintenance Services (parts + onsite/offsite maintenance, repairs, overhaul) | E8: EOI | F8: Services | G8: 46290 | H8: =G8-Overview!$B$3 -> 12 | I8: 25 Sep 2026 | J8: Compressor parts + onsite/offsite maintenance, repairs, overhaul. | K8: Public scope stated; exact quantity not listed | L8: Local Content Register | M8: Local Content Certificate generally required
A9: GY-043 | B9: Private | C9: Halliburton Guyana | D9: Crane Maintenance Services | E9: EOI | F9: Services | G9: 46290 | H9: =G9-Overview!$B$3 -> 12 | I9: 25 Sep 2026 | J9: Crane maintenance (details in notice documents). | K9: Public scope stated; exact quantity not listed | L9: Local Content Register | M9: Local Content Certificate generally required
A10: GY-041 | B10: Private | C10: Oceaneering Guyana | D10: Inland Transportation & Logistics Services - pre-qualify local suppliers | E10: RFI | F10: Services | G10: 46291 | H10: =G10-Overview!$B$3 -> 13 | I10: 26 Sep 2026 | J10: Inland transport and logistics; pre-qualify local suppliers. | K10: Public scope stated; exact quantity not listed | L10: Local Content Register | M10: Local Content Certificate generally required
A11: GY-040 | B11: Private | C11: Tenaris Guyana | D11: RFID Tags Supplier (printer supplier for RFID tags, material traceability project) | E11: RFI | F11: Goods | G11: 46298 | H11: =G11-Overview!$B$3 -> 20 | I11: 3 Oct 2026 | J11: Printer supplier for RFID tags, material traceability project. | K11: Public scope stated; exact quantity not listed | L11: Local Content Register | M11: Local Content Certificate generally required
A12: GY-038 | B12: Private | C12: CNOOC Petroleum Guyana | D12: Janitorial Services - information gathering | E12: RFI | F12: Services | G12: 46300 | H12: =G12-Overview!$B$3 -> 22 | I12: 5 Oct 2026 | J12: Janitorial services; info gathering from qualified providers. | K12: Public scope stated; exact quantity not listed | L12: Local Content Register | M12: Local Content Certificate generally required
A13: GY-039 | B13: Private | C13: Champion X | D13: ISO Tank Inspections (periodic inspections/testing of ISO tanks in chemical logistics) | E13: RFQ | F13: Services | G13: 46300 | H13: =G13-Overview!$B$3 -> 22 | I13: 5 Oct 2026 | J13: Periodic inspections/testing of ISO tanks in chemical logistics. | K13: Public scope stated; exact quantity not listed | L13: Local Content Register | M13: Local Content Certificate generally required
A14: GY-037 | B14: Private | C14: Guyana Shore Base Inc. (GYSBI) | D14: Perimeter Fencing Replacement | E14: RFP | F14: Works | G14: 46302 | H14: =G14-Overview!$B$3 -> 24 | I14: 7 Oct 2026 | J14: Perimeter fencing replacement, Houston EBD. | K14: Public scope stated; exact quantity not listed | L14: Local Content Register | M14: Local Content Certificate generally required
A15: GY-035 | B15: Private | C15: Oceaneering Guyana | D15: Aluminum Welding Services - supplier identification | E15: RFI | F15: Services | G15: 46303 | H15: =G15-Overview!$B$3 -> 25 | I15: 8 Oct 2026 | J15: Aluminum welding for current/future projects; supplier identification. | K15: Public scope stated; exact quantity not listed | L15: Local Content Register | M15: Local Content Certificate generally required
A16: GY-032 | B16: Private | C16: Oceaneering Guyana | D16: Cleaning Supplies (commercial and industrial) - supplier identification | E16: RFI | F16: Goods | G16: 46303 | H16: =G16-Overview!$B$3 -> 25 | I16: 8 Oct 2026 | J16: Supply/availability of cleaning supplies; supplier identification. | K16: Public scope stated; exact quantity not listed | L16: Local Content Register | M16: Local Content Certificate generally required
... A22: GY-029 | B22: Private | C22: Guyana Shore Base Inc. (GYSBI) | D22: Replacement of Water Filter Media | E22: RFP | F22: Goods/Services | G22: 46307 | H22: =G22-Overview!$B$3 -> 29 | I22: 12 Oct 2026 | J22: Replacement of water filter media in the two redundant containerized water treatment plant filters. Quantities not publicly stated. | K22: Full detail in tender documents | L22: Local Content Register | M22: Local Content Certificate generally required
A23: GY-047 | B23: Multilateral | C23: UNDP Guyana (multilateral) | D23: Provision of Unarmed Security Services for the United Nations Offices (Long-Term Agreement) | E23: UNDP-GUY-00034 | F23: Services | I23: Deadline not verified (bids via UNDP Quantum portal) | J23: Unarmed private security guard services: access control, CCTV/alarm monitoring, perimeter security, patrolling, fire-drill assistance. Full TOR on notice page. | K23: Public scope stated; exact quantity not listed | L23: UNDP procurement notice | M23: Verify deadline on notice page before acting

Sheet Verify First
A1: Additional Guyana Opportunities to Verify
A2: These are leads, not counted in the 47 open items. Confirm the notice and closing date before acting.
A4: Status | B4: Opportunity | C4: Entity | D4: Category | E4: Deadline | F4: Why it is not counted yet | G4: Source
A5: Government lead | B5: Hydrometeorological Service - Instructions to Consultants | C5: Ministry of Agriculture / Hydrometeorological Service | D5: Consulting | F5: Details and deadline require reading the scanned advert image. | G5: Official DPI notice
A6: Government lead | B6: Request for Individual Consulting Services - posting 1 | C6: Ministry of Human Services & Social Security | D6: Consulting | F6: Title was indexed; scope and deadline were not machine-readable. | G6: Official DPI notice
A7: Government lead | B7: Request for Individual Consulting Services - posting 2 | C7: Ministry of Human Services & Social Security | D7: Consulting | F7: Title was indexed; scope and deadline were not machine-readable. | G7: Official DPI notice
A8: Government lead | B8: Invitation for Bids posted 4 September 2026 | C8: Guyana Water Inc. | D8: Unknown | F8: Could duplicate an existing GWI order or be a new order. Read the scanned advert before counting it. | G8: Official DPI notice
A9: Government lead | B9: Request for Quotation posted 4 September 2026 | C9: Integrity Commission | D9: Goods/Services | F9: Small-value RFQ. Details and deadline require reading the scanned advert. | G9: Official DPI notice
A10: Possible duplicate | B10: Invitation for Bids posted 9 September 2026 | C10: Ministry of Public Service | D10: Services | F10: Likely the six-location security-services order already in the open list. Verify before treating as separate. | G10: Official DPI notice
A11: Government / multilateral lead | B11: Health Care Network Strengthening in Guyana - Specific Procurement Notice IDB-5706OCGY-P00052 | C11: Government of Guyana / IDB | D11: Unknown | F11: Published around 3 September 2026; procurement details and current deadline were not verified. | G11: IDB project notice
A12: Government / multilateral lead | B12: Supply of Tools and Equipment for Six Practical Instruction Centres, Lots 1-10 | C12: Ministry of Education / Caribbean Development Bank | D12: Goods | F12: Deadline was extended, but current closing date was not verified. | G12: CDB procurement notice

Sheet Guide & Sources
A1: Guide and Source Notes
A2: What is included, what is excluded, and where the data came from
A4: Included
A5: • 28 government opportunities, including four separately published CHPA regional well notices and two Ministry of Home Affairs postings whose closing dates need verification.
A6: • 18 private-sector oil and gas opportunities listed through Guyana’s Local Content Register.
A7: • 1 multilateral procurement notice from UNDP Guyana.
A9: Not counted
A10: • Retracted, expired, awarded, or no-longer-verifiable opportunities.
A11: • Routine Bank of Guyana Treasury Bill tenders, because they are financial-market issues rather than fulfillable procurement orders.
A12: • Public postings with unreadable details or an unverified current deadline. Those are listed separately on Verify First.
A13: • Private companies with no public competitive tender board. Many buy directly or by invitation.
A15: Primary sources
... A25: • Exact technical specifications, delivery terms, volumes, and bills of quantities in the full solicitation document.
